LICENSE
dragon_cache_manager/__init__.py
dragon_cache_manager/apps.py
dragon_cache_manager/forms.py
dragon_cache_manager/management/commands/__init__.py
dragon_cache_manager/management/commands/load_test_cache.py
dragon_cache_manager/management/commands/random_words.txt
dragon_cache_manager/mixins.py
dragon_cache_manager/settings.py
dragon_cache_manager/templates/dragon/base.html
dragon_cache_manager/templates/dragon/button.html
dragon_cache_manager/templates/dragon/redis_key_index.html
dragon_cache_manager/templates/dragon/results.html
dragon_cache_manager/templates/dragon/search.html
dragon_cache_manager/templatetags.py
dragon_cache_manager/urls.py
dragon_cache_manager/utils.py
dragon_cache_manager/views.py
django_dragon-0.1.6.dist-info/LICENSE
django_dragon-0.1.6.dist-info/WHEEL
django_dragon-0.1.6.dist-info/METADATA
django_dragon-0.1.6.dist-info/RECORD
