Metadata-Version: 2.1
Name: django-dragon
Version: 0.1.6
Summary: A cache manager for Django admin
Home-page: https://github.com/Lenders-Cooperative/django-dragon
License: BSD-3-Clause
Author: Logan Bibby
Author-email: lbibby@thesummitgrp.com
Requires-Python: >=3.6,<4.0
Classifier: License :: OSI Approved :: BSD License
Classifier: Programming Language :: Python :: 3
Classifier: Programming Language :: Python :: 3.6
Classifier: Programming Language :: Python :: 3.7
Classifier: Programming Language :: Python :: 3.8
Classifier: Programming Language :: Python :: 3.9
Requires-Dist: Django (>=3.1.13,<4.0.0)
